{"route":{"from":"EGE","to":"JFK","total_flights":1107,"year_min":2018,"year_max":2026},"accuracy":{"dep":{"perfect":60.0,"standard":9.1,"disruptive":30.9},"arr":{"perfect":62.5,"standard":8.8,"disruptive":28.8},"mean_dep_delay":33.9,"mean_arr_delay":25.5},"accuracy_by_year":{"2018":{"dep":{"perfect":79.2,"standard":6.2,"disruptive":14.7},"arr":{"perfect":78.5,"standard":5.5,"disruptive":16.0}},"2019":{"dep":{"perfect":48.6,"standard":15.7,"disruptive":35.7},"arr":{"perfect":45.7,"standard":14.3,"disruptive":40.0}},"2020":{"dep":{"perfect":71.1,"standard":6.7,"disruptive":22.2},"arr":{"perfect":78.9,"standard":3.3,"disruptive":17.8}},"2021":{"dep":{"perfect":64.1,"standard":6.8,"disruptive":29.1},"arr":{"perfect":71.8,"standard":6.8,"disruptive":21.4}},"2022":{"dep":{"perfect":58.4,"standard":10.9,"disruptive":30.7},"arr":{"perfect":60.4,"standard":8.9,"disruptive":30.7}},"2023":{"dep":{"perfect":51.9,"standard":10.6,"disruptive":37.5},"arr":{"perfect":46.2,"standard":14.4,"disruptive":39.4}},"2024":{"dep":{"perfect":53.9,"standard":5.9,"disruptive":40.2},"arr":{"perfect":50.0,"standard":10.8,"disruptive":39.2}},"2025":{"dep":{"perfect":45.3,"standard":10.4,"disruptive":44.3},"arr":{"perfect":54.7,"standard":11.3,"disruptive":34.0}},"2026":{"dep":{"perfect":27.5,"standard":16.7,"disruptive":55.9},"arr":{"perfect":41.2,"standard":10.8,"disruptive":48.0}}},"insight":"Airlines make up time in the air on 2% of delayed departures, resulting in better arrival accuracy than departure accuracy.","heatmap":[[0.0,31.7,null,null],[8.8,24.8,null,null],[14.7,34.6,null,null],[43.3,29.6,null,null],[37.0,36.9,null,null],[9.4,41.0,null,null],[17.2,39.5,null,null]],"arr_heatmap":[[0.0,25.0,null,null],[23.5,23.0,null,null],[0.0,30.8,null,null],[53.3,32.0,null,null],[18.5,34.4,null,null],[0.0,38.2,null,null],[34.5,35.5,null,null]],"monthly_heatmap":[[[0.0,50.0,null,null],[0.0,23.3,null,null],[20.0,33.3,null,null],[66.7,38.2,null,null],[66.7,39.4,null,null],[0.0,45.9,null,null],[25.0,41.9,null,null]],[[0.0,31.0,null,null],[null,28.6,null,null],[null,32.1,null,null],[25.0,33.3,null,null],[0.0,32.3,null,null],[25.0,36.1,null,null],[null,41.4,null,null]],[[null,17.1,null,null],[null,11.9,null,null],[null,31.2,null,null],[null,16.3,null,null],[null,26.8,null,null],[null,35.4,null,null],[null,36.4,null,null]],[[null,null,null,null],[null,null,null,null],[null,null,null,null],[null,null,null,null],[null,null,null,null],[null,null,null,null],[null,null,null,null]],[[null,null,null,null],[null,null,null,null],[null,null,null,null],[null,null,null,null],[null,null,null,null],[null,null,null,null],[null,null,null,null]],[[null,null,null,null],[null,null,null,null],[null,null,null,null],[null,null,null,null],[null,null,null,null],[null,null,null,null],[null,null,null,null]],[[null,null,null,null],[null,null,null,null],[null,null,null,null],[null,null,null,null],[null,null,null,null],[null,null,null,null],[null,null,null,null]],[[null,null,null,null],[null,null,null,null],[null,null,null,null],[null,null,null,null],[null,null,null,null],[null,null,null,null],[null,null,null,null]],[[null,null,null,null],[null,null,null,null],[null,null,null,null],[null,null,null,null],[null,null,null,null],[null,null,null,null],[null,null,null,null]],[[null,null,null,null],[null,null,null,null],[null,null,null,null],[null,null,null,null],[null,null,null,null],[null,null,null,null],[null,null,null,null]],[[null,null,null,null],[null,null,null,null],[null,null,null,null],[null,null,null,null],[null,null,null,null],[null,null,null,null],[null,null,null,null]],[[null,54.5,null,null],[null,63.6,null,null],[null,45.5,null,null],[null,37.5,null,null],[null,64.3,null,null],[null,57.9,null,null],[null,53.8,null,null]]],"arr_monthly_heatmap":[[[0.0,40.6,null,null],[20.0,26.7,null,null],[0.0,26.7,null,null],[66.7,35.3,null,null],[33.3,45.5,null,null],[0.0,37.8,null,null],[50.0,41.9,null,null]],[[0.0,24.1,null,null],[null,25.0,null,null],[null,28.6,null,null],[50.0,33.3,null,null],[0.0,25.8,null,null],[0.0,30.6,null,null],[null,31.0,null,null]],[[null,12.2,null,null],[null,9.5,null,null],[null,31.2,null,null],[null,27.9,null,null],[null,22.0,null,null],[null,35.4,null,null],[null,31.8,null,null]],[[null,null,null,null],[null,null,null,null],[null,null,null,null],[null,null,null,null],[null,null,null,null],[null,null,null,null],[null,null,null,null]],[[null,null,null,null],[null,null,null,null],[null,null,null,null],[null,null,null,null],[null,null,null,null],[null,null,null,null],[null,null,null,null]],[[null,null,null,null],[null,null,null,null],[null,null,null,null],[null,null,null,null],[null,null,null,null],[null,null,null,null],[null,null,null,null]],[[null,null,null,null],[null,null,null,null],[null,null,null,null],[null,null,null,null],[null,null,null,null],[null,null,null,null],[null,null,null,null]],[[null,null,null,null],[null,null,null,null],[null,null,null,null],[null,null,null,null],[null,null,null,null],[null,null,null,null],[null,null,null,null]],[[null,null,null,null],[null,null,null,null],[null,null,null,null],[null,null,null,null],[null,null,null,null],[null,null,null,null],[null,null,null,null]],[[null,null,null,null],[null,null,null,null],[null,null,null,null],[null,null,null,null],[null,null,null,null],[null,null,null,null],[null,null,null,null]],[[null,null,null,null],[null,null,null,null],[null,null,null,null],[null,null,null,null],[null,null,null,null],[null,null,null,null],[null,null,null,null]],[[null,45.5,null,null],[null,54.5,null,null],[null,45.5,null,null],[null,37.5,null,null],[null,57.1,null,null],[null,63.2,null,null],[null,53.8,null,null]]],"monthly":[36.8,31.1,30.4,null,null,null,null,null,null,null,null,51.9],"arr_monthly":[30.5,24.1,24.1,21.4,null,null,null,null,null,null,null,50.0],"monthly_by_year":{"2018":[21.4,11.5,0.0,null,null,null,null,null,null,null,null,54.5],"2019":[47.8,25.0,42.9,null,null,null,null,null,null,null,null,35.7],"2020":[26.7,17.9,29.4,null,null,null,null,null,null,null,null,13.3],"2021":[13.8,40.0,26.7,null,null,null,null,null,null,null,null,50.0],"2022":[22.2,30.8,19.4,null,null,null,null,null,null,null,null,73.3],"2023":[53.3,35.7,32.3,null,null,null,null,null,null,null,null,25.0],"2024":[46.7,20.7,35.5,null,null,null,null,null,null,null,null,81.8],"2025":[35.5,57.1,25.8,null,null,null,null,null,null,null,null,81.3],"2026":[63.6,41.4,61.8,null,null,null,null,null,null,null,null,null]},"monthly_counts":[373,291,307,28,0,0,0,0,0,0,0,108],"carriers":[{"code":"AA","name":"American Airlines","vol":1093,"dep_delay":33.6,"arr_delay":25.0,"cancel_pct":0.0,"causes":{"carrier":82.1,"weather":2.0,"nas":9.7,"late_aircraft":55.3}}],"annual":{"baseline":[{"year":2018,"arr_delay":22.6,"dep_delay":33.9,"flights":307},{"year":2019,"arr_delay":42.8,"dep_delay":47.9,"flights":70},{"year":2020,"arr_delay":-2.4,"dep_delay":11.9,"flights":90},{"year":2021,"arr_delay":4.2,"dep_delay":20.4,"flights":103},{"year":2022,"arr_delay":20.3,"dep_delay":24.6,"flights":101},{"year":2023,"arr_delay":22.6,"dep_delay":23.8,"flights":104},{"year":2024,"arr_delay":56.2,"dep_delay":56.1,"flights":102},{"year":2025,"arr_delay":21.9,"dep_delay":34.2,"flights":106},{"year":2026,"arr_delay":50.1,"dep_delay":54.7,"flights":102}],"by_carrier":{"AA":[{"year":2018,"arr_delay":22.6,"dep_delay":33.9,"flights":307},{"year":2019,"arr_delay":42.8,"dep_delay":47.9,"flights":70},{"year":2020,"arr_delay":-2.4,"dep_delay":11.9,"flights":90},{"year":2021,"arr_delay":4.2,"dep_delay":20.4,"flights":103},{"year":2022,"arr_delay":20.3,"dep_delay":24.6,"flights":101},{"year":2023,"arr_delay":22.6,"dep_delay":23.8,"flights":104},{"year":2024,"arr_delay":56.2,"dep_delay":56.1,"flights":102},{"year":2025,"arr_delay":18.7,"dep_delay":31.0,"flights":104},{"year":2026,"arr_delay":51.2,"dep_delay":56.0,"flights":90}]}}}