{"route":{"from":"IND","to":"PIE","total_flights":2735,"year_min":2018,"year_max":2026},"accuracy":{"dep":{"perfect":72.6,"standard":8.5,"disruptive":18.8},"arr":{"perfect":66.3,"standard":9.9,"disruptive":23.7},"mean_dep_delay":12.7,"mean_arr_delay":12.7},"accuracy_by_year":{"2018":{"dep":{"perfect":70.5,"standard":10.0,"disruptive":19.5},"arr":{"perfect":64.5,"standard":10.0,"disruptive":25.5}},"2019":{"dep":{"perfect":82.4,"standard":4.2,"disruptive":13.4},"arr":{"perfect":73.5,"standard":7.7,"disruptive":18.8}},"2020":{"dep":{"perfect":85.7,"standard":3.2,"disruptive":11.1},"arr":{"perfect":81.7,"standard":5.6,"disruptive":12.7}},"2021":{"dep":{"perfect":68.5,"standard":9.7,"disruptive":21.8},"arr":{"perfect":60.6,"standard":14.2,"disruptive":25.3}},"2022":{"dep":{"perfect":65.7,"standard":11.6,"disruptive":22.7},"arr":{"perfect":54.2,"standard":15.5,"disruptive":30.3}},"2023":{"dep":{"perfect":74.7,"standard":7.5,"disruptive":17.8},"arr":{"perfect":72.2,"standard":7.5,"disruptive":20.3}},"2024":{"dep":{"perfect":68.5,"standard":7.8,"disruptive":23.7},"arr":{"perfect":65.8,"standard":7.8,"disruptive":26.5}},"2025":{"dep":{"perfect":68.1,"standard":10.5,"disruptive":21.4},"arr":{"perfect":60.9,"standard":10.1,"disruptive":29.0}},"2026":{"dep":{"perfect":66.2,"standard":15.4,"disruptive":18.5},"arr":{"perfect":66.2,"standard":12.3,"disruptive":21.5}}},"insight":"Arrival delays run 5% higher than departure delays \u2014 congestion at PIE worsens on-time performance after landing.","heatmap":[[9.6,20.0,31.0,25.0],[10.1,11.1,4.3,null],[7.1,17.6,21.5,null],[8.6,13.1,27.0,36.1],[6.8,21.4,41.0,38.2],[10.5,17.4,22.0,50.0],[8.7,21.7,32.3,34.1]],"arr_heatmap":[[10.4,20.0,50.0,27.5],[10.1,22.2,8.7,null],[13.1,21.6,28.0,null],[14.2,16.8,28.7,38.9],[10.2,19.4,50.8,35.3],[17.0,24.8,26.0,45.8],[13.3,27.1,37.9,34.1]],"monthly_heatmap":[[[null,null,29.2,null],[null,0.0,null,null],[null,null,19.2,null],[0.0,7.7,27.3,null],[0.0,null,27.3,null],[0.0,17.6,null,null],[16.7,23.1,50.0,null]],[[18.2,null,null,null],[null,0.0,null,null],[0.0,null,null,null],[6.7,25.0,37.5,null],[0.0,null,null,null],[18.8,43.8,9.1,null],[7.1,21.4,40.0,null]],[[14.3,36.4,null,null],[15.4,0.0,null,null],[6.7,9.7,null,null],[null,18.8,20.0,null],[0.0,34.6,10.0,null],[9.1,29.2,30.0,54.5],[null,46.2,26.3,null]],[[null,46.2,18.2,null],[null,null,null,null],[null,null,28.6,null],[null,9.5,null,null],[null,null,60.0,null],[6.7,5.6,10.0,null],[null,23.8,30.0,null]],[[16.7,9.1,null,null],[null,null,null,null],[null,null,20.0,null],[10.0,null,null,null],[15.4,23.1,null,null],[26.7,5.6,null,null],[3.8,0.0,null,null]],[[null,null,47.1,27.3],[25.0,null,null,null],[18.2,null,15.8,null],[17.4,null,45.5,null],[9.1,null,64.3,30.0],[12.5,6.7,null,null],[12.5,null,28.6,null]],[[0.0,null,43.5,null],[4.5,null,null,null],[10.0,null,35.0,null],[18.2,null,16.7,null],[18.2,null,72.7,null],[16.0,null,null,null],[8.7,null,15.4,null]],[[null,null,null,null],[null,null,null,null],[null,null,null,null],[23.5,null,null,null],[null,null,null,null],[21.4,null,null,null],[5.6,null,null,null]],[[null,10.0,null,null],[null,null,null,null],[null,null,null,null],[0.0,null,null,null],[null,null,null,null],[null,null,null,null],[17.6,null,null,null]],[[0.0,7.7,null,null],[9.1,null,null,null],[0.0,null,null,null],[0.0,7.1,null,null],[5.6,null,null,null],[10.5,5.6,null,null],[0.0,21.4,null,null]],[[null,10.0,null,null],[null,null,null,null],[null,null,null,null],[7.1,13.3,null,null],[null,21.4,null,null],[0.0,null,null,null],[7.1,30.8,null,null]],[[null,null,null,null],[null,null,null,null],[null,null,null,null],[0.0,16.7,null,null],[0.0,null,null,null],[0.0,27.3,null,null],[11.8,23.5,null,null]]],"arr_monthly_heatmap":[[[null,null,50.0,null],[null,23.8,null,null],[null,null,38.5,null],[5.0,15.4,27.3,null],[10.0,null,45.5,null],[3.7,17.6,null,null],[38.9,38.5,50.0,null]],[[27.3,null,null,null],[null,6.7,null,null],[10.5,null,null,null],[26.7,25.0,31.2,null],[27.3,null,null,null],[18.8,43.8,36.4,null],[21.4,28.6,60.0,null]],[[7.1,36.4,null,null],[15.4,0.0,null,null],[6.7,9.7,null,null],[null,25.0,20.0,null],[0.0,26.9,20.0,null],[22.7,45.8,26.7,54.5],[null,46.2,26.3,null]],[[null,23.1,63.6,null],[null,null,null,null],[null,null,28.6,null],[null,9.5,null,null],[null,null,70.0,null],[26.7,5.6,20.0,null],[null,42.9,30.0,null]],[[16.7,18.2,null,null],[null,null,null,null],[null,null,20.0,null],[10.0,null,null,null],[15.4,15.4,null,null],[26.7,27.8,null,null],[3.8,0.0,null,null]],[[null,null,82.4,27.3],[25.0,null,null,null],[27.3,null,21.1,null],[17.4,null,36.4,null],[9.1,null,78.6,20.0],[12.5,13.3,null,null],[12.5,null,35.7,null]],[[0.0,null,60.9,null],[4.5,null,null,null],[20.0,null,40.0,null],[18.2,null,33.3,null],[9.1,null,81.8,null],[16.0,null,null,null],[8.7,null,23.1,null]],[[null,null,null,null],[null,null,null,null],[null,null,null,null],[23.5,null,null,null],[null,null,null,null],[28.6,null,null,null],[11.1,null,null,null]],[[null,20.0,null,null],[null,null,null,null],[null,null,null,null],[0.0,null,null,null],[null,null,null,null],[null,null,null,null],[17.6,null,null,null]],[[0.0,7.7,null,null],[9.1,null,null,null],[0.0,null,null,null],[10.0,21.4,null,null],[5.6,null,null,null],[15.8,5.6,null,null],[0.0,21.4,null,null]],[[null,20.0,null,null],[null,null,null,null],[null,null,null,null],[21.4,13.3,null,null],[null,21.4,null,null],[0.0,null,null,null],[7.1,30.8,null,null]],[[null,null,null,null],[null,null,null,null],[null,null,null,null],[14.3,16.7,null,null],[10.0,null,null,null],[28.6,36.4,null,null],[17.6,17.6,null,null]]],"monthly":[14.1,18.3,17.7,22.3,17.9,27.7,27.5,20.0,10.0,11.6,13.2,17.6],"arr_monthly":[26.6,26.3,22.4,27.6,18.3,31.1,31.1,27.8,12.9,12.8,16.2,23.4],"monthly_by_year":{"2018":[19.4,17.9,31.4,17.9,11.1,24.1,22.6,29.2,4.5,10.0,11.5,3.8],"2019":[4.3,8.7,12.8,16.1,25.0,20.0,12.9,25.0,4.3,5.9,11.1,11.5],"2020":[4.3,25.0,5.9,null,5.6,19.0,11.1,21.7,5.0,10.3,11.8,5.6],"2021":[9.1,15.8,7.7,16.7,20.0,34.5,33.3,13.6,33.3,29.0,19.0,28.6],"2022":[28.6,29.4,26.5,28.6,22.7,32.0,23.1,30.8,8.3,9.4,11.1,22.2],"2023":[7.1,15.4,14.8,31.6,0.0,26.9,55.6,0.0,6.7,3.2,10.5,19.0],"2024":[13.3,21.4,27.6,7.7,17.6,38.5,32.0,40.0,18.2,9.1,23.1,25.0],"2025":[17.6,23.1,18.5,30.0,40.9,26.7,29.6,0.0,0.0,16.0,7.1,25.0],"2026":[23.5,7.7,14.3,30.0,null,null,null,null,null,null,null,null]},"monthly_counts":[289,220,362,228,230,274,286,146,133,234,155,178],"carriers":[{"code":"G4","name":"Allegiant Air","vol":2735,"dep_delay":12.7,"arr_delay":12.7,"cancel_pct":0.0,"causes":{"carrier":32.3,"weather":4.8,"nas":13.2,"late_aircraft":40.2}}],"annual":{"baseline":[{"year":2018,"arr_delay":16.4,"dep_delay":16.8,"flights":816},{"year":2019,"arr_delay":6.5,"dep_delay":7.5,"flights":336},{"year":2020,"arr_delay":-0.2,"dep_delay":1.1,"flights":252},{"year":2021,"arr_delay":13.3,"dep_delay":12.1,"flights":289},{"year":2022,"arr_delay":18.1,"dep_delay":13.6,"flights":251},{"year":2023,"arr_delay":10.5,"dep_delay":11.4,"flights":241},{"year":2024,"arr_delay":12.5,"dep_delay":15.1,"flights":219},{"year":2025,"arr_delay":17.7,"dep_delay":15.2,"flights":248},{"year":2026,"arr_delay":16.9,"dep_delay":19.8,"flights":65}],"by_carrier":{"G4":[{"year":2018,"arr_delay":16.4,"dep_delay":16.8,"flights":816},{"year":2019,"arr_delay":6.5,"dep_delay":7.5,"flights":336},{"year":2020,"arr_delay":-0.2,"dep_delay":1.1,"flights":252},{"year":2021,"arr_delay":13.3,"dep_delay":12.1,"flights":289},{"year":2022,"arr_delay":18.1,"dep_delay":13.6,"flights":251},{"year":2023,"arr_delay":10.5,"dep_delay":11.4,"flights":241},{"year":2024,"arr_delay":12.5,"dep_delay":15.1,"flights":219},{"year":2025,"arr_delay":17.7,"dep_delay":15.2,"flights":248},{"year":2026,"arr_delay":16.9,"dep_delay":19.8,"flights":65}]}}}