{"route":{"from":"MCI","to":"IND","total_flights":3525,"year_min":2018,"year_max":2026},"accuracy":{"dep":{"perfect":68.8,"standard":11.2,"disruptive":19.9},"arr":{"perfect":73.9,"standard":8.6,"disruptive":17.5},"mean_dep_delay":10.7,"mean_arr_delay":4.7},"accuracy_by_year":{"2018":{"dep":{"perfect":70.8,"standard":9.6,"disruptive":19.6},"arr":{"perfect":73.8,"standard":8.7,"disruptive":17.5}},"2019":{"dep":{"perfect":71.5,"standard":9.7,"disruptive":18.8},"arr":{"perfect":74.8,"standard":7.3,"disruptive":18.0}},"2020":{"dep":{"perfect":88.4,"standard":7.7,"disruptive":3.9},"arr":{"perfect":92.3,"standard":5.8,"disruptive":1.9}},"2023":{"dep":{"perfect":66.9,"standard":11.8,"disruptive":21.3},"arr":{"perfect":73.1,"standard":9.5,"disruptive":17.4}},"2024":{"dep":{"perfect":61.8,"standard":13.9,"disruptive":24.2},"arr":{"perfect":72.4,"standard":10.3,"disruptive":17.4}},"2025":{"dep":{"perfect":60.5,"standard":15.6,"disruptive":23.9},"arr":{"perfect":66.6,"standard":8.4,"disruptive":25.1}},"2026":{"dep":{"perfect":57.0,"standard":21.5,"disruptive":21.5},"arr":{"perfect":74.8,"standard":10.3,"disruptive":15.0}}},"insight":"Airlines make up time in the air on 2% of delayed departures, resulting in better arrival accuracy than departure accuracy.","heatmap":[[3.6,9.4,33.3,22.7],[11.1,9.3,27.6,19.1],[4.9,9.0,21.3,27.1],[7.8,25.2,34.8,38.5],[9.9,12.7,42.4,23.7],[7.9,13.4,32.4,null],[19.6,10.3,33.6,25.0]],"arr_heatmap":[[2.9,11.7,29.0,15.9],[13.9,5.4,31.0,15.8],[5.6,6.0,14.6,23.2],[9.2,17.3,28.3,39.0],[11.3,12.7,33.3,19.0],[0.0,14.4,24.3,null],[19.6,8.3,30.9,21.4]],"monthly_heatmap":[[[null,0.0,null,21.2],[null,14.7,null,15.2],[null,2.9,10.0,20.6],[null,34.4,null,41.4],[null,0.0,50.0,4.0],[null,null,null,null],[null,9.4,12.5,null]],[[null,5.9,null,0.0],[null,0.0,null,17.6],[null,0.0,0.0,7.1],[null,52.9,null,35.0],[null,29.4,null,30.0],[null,null,null,null],[null,25.0,11.1,null]],[[0.0,16.7,21.4,8.3],[18.8,7.1,0.0,15.4],[0.0,0.0,0.0,0.0],[18.8,16.7,25.0,18.2],[17.6,5.6,52.9,16.7],[null,null,null,null],[null,7.1,41.4,null]],[[4.2,null,null,16.0],[22.7,null,45.5,33.3],[0.0,null,50.0,14.3],[0.0,null,null,37.5],[0.0,null,null,26.1],[null,null,null,null],[26.7,null,36.4,null]],[[0.0,null,null,40.0],[8.7,null,null,8.7],[12.0,null,null,60.0],[8.3,null,null,41.4],[0.0,null,null,22.2],[null,25.0,null,null],[25.0,null,61.9,null]],[[6.2,null,null,28.6],[0.0,null,null,10.0],[0.0,null,null,50.0],[17.6,null,null,42.9],[20.0,null,null,25.0],[0.0,27.3,null,null],[null,16.7,38.9,null]],[[0.0,null,null,40.0],[17.6,null,30.8,14.3],[21.4,null,23.1,22.2],[0.0,null,null,26.3],[37.5,null,null,30.0],[25.0,null,null,null],[null,8.3,45.0,null]],[[10.0,null,null,21.4],[0.0,7.7,null,60.0],[0.0,15.4,null,22.2],[7.1,null,null,42.1],[0.0,null,20.0,31.2],[null,7.7,null,null],[null,0.0,null,null]],[[null,null,0.0,30.8],[0.0,null,null,25.0],[8.3,null,null,25.0],[null,null,null,58.3],[null,null,null,53.8],[null,7.7,null,null],[null,10.0,null,null]],[[15.4,null,null,14.3],[13.3,null,null,20.0],[0.0,null,null,57.1],[7.7,50.0,null,61.5],[0.0,null,null,16.7],[null,null,null,null],[null,8.3,null,null]],[[null,15.4,null,20.0],[null,20.0,null,10.0],[null,7.1,null,null],[null,0.0,null,30.0],[null,null,10.0,25.0],[null,20.0,null,null],[null,0.0,31.2,null]],[[null,7.1,null,null],[null,8.3,20.0,null],[null,0.0,null,null],[null,8.3,null,null],[null,8.3,null,null],[null,null,null,null],[null,15.4,35.7,null]]],"arr_monthly_heatmap":[[[null,15.2,null,6.1],[null,0.0,null,0.0],[null,0.0,10.0,17.6],[null,31.2,null,41.4],[null,0.0,40.0,4.0],[null,null,null,null],[null,6.2,29.2,null]],[[null,5.9,null,0.0],[null,0.0,null,5.9],[null,0.0,0.0,7.1],[null,17.6,null,30.0],[null,29.4,null,15.0],[null,null,null,null],[null,20.0,5.6,null]],[[0.0,16.7,21.4,8.3],[25.0,7.1,27.3,15.4],[0.0,0.0,0.0,0.0],[18.8,11.1,18.8,18.2],[17.6,5.6,17.6,16.7],[null,null,null,null],[null,7.1,37.9,null]],[[4.2,null,null,16.0],[22.7,null,45.5,38.1],[0.0,null,20.0,14.3],[0.0,null,null,41.7],[4.8,null,null,26.1],[null,null,null,null],[26.7,null,36.4,null]],[[0.0,null,null,36.0],[4.3,null,null,8.7],[12.0,null,null,52.0],[4.2,null,null,41.4],[0.0,null,null,14.8],[null,25.0,null,null],[25.0,null,61.9,null]],[[6.2,null,null,23.8],[18.8,null,null,10.0],[0.0,null,null,50.0],[35.3,null,null,42.9],[20.0,null,null,16.7],[0.0,36.4,null,null],[null,8.3,38.9,null]],[[0.0,null,null,24.0],[17.6,null,30.8,14.3],[21.4,null,30.8,22.2],[0.0,null,null,47.4],[37.5,null,null,30.0],[0.0,null,null,null],[null,8.3,20.0,null]],[[10.0,null,null,14.3],[0.0,7.7,null,46.7],[7.7,7.7,null,22.2],[7.1,null,null,42.1],[8.3,null,20.0,25.0],[null,15.4,null,null],[null,0.0,null,null]],[[null,null,0.0,15.4],[0.0,null,null,25.0],[0.0,null,null,16.7],[null,null,null,50.0],[null,null,null,38.5],[null,0.0,null,null],[null,10.0,null,null]],[[7.7,null,null,7.1],[13.3,null,null,26.7],[0.0,null,null,35.7],[15.4,50.0,null,46.2],[0.0,null,null,16.7],[null,null,null,null],[null,0.0,null,null]],[[null,7.7,null,10.0],[null,20.0,null,10.0],[null,7.1,null,null],[null,0.0,null,30.0],[null,null,10.0,25.0],[null,10.0,null,null],[null,0.0,25.0,null]],[[null,7.1,null,null],[null,8.3,20.0,null],[null,7.1,null,null],[null,0.0,null,null],[null,0.0,null,null],[null,null,null,null],[null,23.1,28.6,null]]],"monthly":[17.8,16.1,15.3,17.6,33.7,30.5,29.0,17.4,18.0,19.9,18.2,15.9],"arr_monthly":[13.3,11.4,14.4,20.0,24.3,24.4,23.6,15.6,14.5,17.6,14.5,13.2],"monthly_by_year":{"2018":[15.1,20.5,18.4,25.9,20.3,15.4,25.5,14.3,24.0,15.5,30.0,13.5],"2019":[15.6,14.6,10.9,23.5,35.3,34.0,12.3,15.8,14.5,22.4,13.7,11.3],"2020":[2.1,7.4,4.5,2.9,null,null,null,null,null,null,null,null],"2023":[null,null,null,13.8,26.0,25.0,36.0,28.6,23.1,18.9,6.3,8.7],"2024":[40.6,24.0,20.9,18.8,40.7,37.9,45.2,8.8,11.8,11.4,14.3,23.3],"2025":[18.5,4.2,11.5,19.2,46.2,40.0,25.8,19.4,16.7,31.4,26.7,22.6],"2026":[14.8,25.9,25.9,19.2,null,null,null,null,null,null,null,null]},"monthly_counts":[444,276,333,360,333,316,322,262,221,239,207,212],"carriers":[{"code":"WN","name":"Southwest Airlines","vol":3525,"dep_delay":10.7,"arr_delay":4.7,"cancel_pct":0.0,"causes":{"carrier":16.6,"weather":0.4,"nas":2.8,"late_aircraft":41.3}}],"annual":{"baseline":[{"year":2018,"arr_delay":5.3,"dep_delay":10.6,"flights":1483},{"year":2019,"arr_delay":4.5,"dep_delay":9.8,"flights":618},{"year":2020,"arr_delay":-9.4,"dep_delay":-2.0,"flights":155},{"year":2023,"arr_delay":4.8,"dep_delay":13.2,"flights":432},{"year":2024,"arr_delay":6.2,"dep_delay":13.6,"flights":380},{"year":2025,"arr_delay":8.8,"dep_delay":12.7,"flights":347},{"year":2026,"arr_delay":0.9,"dep_delay":9.2,"flights":107}],"by_carrier":{"WN":[{"year":2018,"arr_delay":5.3,"dep_delay":10.6,"flights":1483},{"year":2019,"arr_delay":4.5,"dep_delay":9.8,"flights":618},{"year":2020,"arr_delay":-9.4,"dep_delay":-2.0,"flights":155},{"year":2023,"arr_delay":4.8,"dep_delay":13.2,"flights":432},{"year":2024,"arr_delay":6.2,"dep_delay":13.6,"flights":380},{"year":2025,"arr_delay":8.8,"dep_delay":12.7,"flights":347},{"year":2026,"arr_delay":0.9,"dep_delay":9.2,"flights":107}]}}}