{"route":{"from":"ORD","to":"PBI","total_flights":9370,"year_min":2018,"year_max":2026},"accuracy":{"dep":{"perfect":74.5,"standard":7.4,"disruptive":18.1},"arr":{"perfect":70.1,"standard":8.7,"disruptive":21.1},"mean_dep_delay":9.7,"mean_arr_delay":4.9},"accuracy_by_year":{"2018":{"dep":{"perfect":78.2,"standard":7.1,"disruptive":14.7},"arr":{"perfect":70.9,"standard":9.8,"disruptive":19.3}},"2019":{"dep":{"perfect":73.4,"standard":9.2,"disruptive":17.5},"arr":{"perfect":69.2,"standard":10.7,"disruptive":20.1}},"2020":{"dep":{"perfect":83.0,"standard":6.2,"disruptive":10.9},"arr":{"perfect":81.4,"standard":7.0,"disruptive":11.6}},"2021":{"dep":{"perfect":78.8,"standard":6.9,"disruptive":14.3},"arr":{"perfect":76.7,"standard":7.2,"disruptive":16.1}},"2022":{"dep":{"perfect":64.8,"standard":10.3,"disruptive":24.9},"arr":{"perfect":60.5,"standard":9.1,"disruptive":30.5}},"2023":{"dep":{"perfect":74.1,"standard":8.0,"disruptive":17.9},"arr":{"perfect":70.5,"standard":7.7,"disruptive":21.8}},"2024":{"dep":{"perfect":71.2,"standard":7.3,"disruptive":21.5},"arr":{"perfect":70.0,"standard":7.3,"disruptive":22.7}},"2025":{"dep":{"perfect":71.1,"standard":6.3,"disruptive":22.6},"arr":{"perfect":66.3,"standard":8.7,"disruptive":25.0}},"2026":{"dep":{"perfect":61.3,"standard":8.1,"disruptive":30.6},"arr":{"perfect":58.4,"standard":9.0,"disruptive":32.6}}},"insight":"Arrival delays run 3% higher than departure delays \u2014 congestion at PBI worsens on-time performance after landing.","heatmap":[[18.6,19.9,24.1,25.0],[10.8,14.9,26.3,30.4],[11.5,18.9,18.6,26.3],[10.7,21.4,28.8,32.4],[15.3,23.7,24.6,42.9],[13.1,18.5,26.7,34.7],[11.6,21.1,27.7,41.5]],"arr_heatmap":[[19.6,23.0,17.6,35.7],[11.4,18.2,25.3,30.4],[17.7,21.2,26.5,36.8],[13.2,26.4,30.1,41.2],[18.1,25.0,29.9,40.0],[14.9,21.0,25.2,36.7],[17.7,27.6,27.7,41.5]],"monthly_heatmap":[[[20.5,24.8,16.7,null],[7.5,15.8,35.0,null],[8.3,22.8,13.6,null],[0.0,16.2,30.8,null],[4.7,30.4,30.8,null],[4.3,12.1,25.0,null],[21.1,8.1,23.7,null]],[[15.2,10.7,14.8,null],[13.3,11.1,5.0,null],[6.2,16.0,25.0,null],[12.1,22.2,26.7,null],[8.2,28.4,22.2,null],[13.6,16.7,18.5,null],[13.1,28.0,30.3,null]],[[11.8,19.8,16.7,null],[13.0,13.6,40.0,null],[7.4,10.5,22.6,null],[9.0,16.7,30.0,null],[17.6,18.0,26.8,null],[16.7,29.0,39.5,null],[14.3,22.4,40.0,null]],[[21.5,13.6,50.0,null],[9.2,11.9,null,null],[18.2,17.9,null,null],[8.8,19.5,null,null],[18.0,30.7,20.0,null],[11.1,12.9,12.5,null],[9.7,23.0,15.4,null]],[[40.0,25.5,null,null],[2.8,24.0,null,null],[10.0,20.8,null,null],[24.5,20.4,null,null],[13.3,18.0,null,null],[7.5,4.1,null,null],[1.9,8.3,null,null]],[[28.0,35.3,null,null],[8.7,29.4,null,null],[28.6,13.3,null,null],[4.2,29.0,null,null],[30.0,58.6,null,null],[9.7,15.8,null,null],[6.9,23.5,null,null]],[[16.7,36.1,null,null],[9.7,10.5,null,null],[3.6,35.5,null,null],[7.1,40.0,null,null],[28.6,15.2,null,null],[21.4,18.8,null,null],[9.7,25.7,null,null]],[[12.5,27.3,null,null],[5.3,10.0,null,null],[21.7,15.8,null,null],[16.0,21.7,null,null],[26.9,15.4,null,null],[31.6,21.7,null,null],[4.0,25.0,null,null]],[[null,18.5,null,null],[null,10.0,null,null],[null,15.0,null,null],[null,15.4,null,null],[null,4.5,null,null],[null,21.4,null,null],[null,14.8,null,null]],[[14.3,11.4,null,null],[12.5,12.5,null,null],[10.5,16.7,null,null],[14.3,17.6,null,null],[15.8,11.8,null,null],[14.3,25.0,null,null],[18.2,14.7,null,null]],[[12.1,16.3,null,null],[22.9,12.5,null,null],[11.8,18.4,null,null],[10.3,15.0,null,null],[8.8,8.9,null,20.0],[17.1,8.3,null,29.4],[8.6,17.0,null,40.0]],[[11.5,13.8,50.0,25.0],[11.1,16.4,15.4,null],[12.2,26.4,20.0,null],[15.2,35.1,22.2,20.0],[20.0,27.6,21.1,54.5],[16.7,36.1,26.3,40.0],[8.5,43.3,29.4,53.8]]],"arr_monthly_heatmap":[[[28.9,32.7,5.6,null],[12.5,13.2,30.0,null],[17.9,28.9,18.2,null],[3.7,20.7,30.8,null],[15.3,43.1,38.5,null],[4.3,19.6,35.0,null],[25.0,19.2,23.7,null]],[[16.7,9.5,11.1,null],[11.7,12.3,10.0,null],[23.1,17.3,30.0,null],[22.7,30.0,30.0,null],[9.8,25.9,18.5,null],[21.2,16.7,25.9,null],[31.1,34.1,27.3,null]],[[15.8,20.9,10.0,null],[14.3,22.2,48.0,null],[16.0,16.3,35.5,null],[12.8,19.8,32.5,null],[17.6,19.0,31.7,null],[14.3,30.8,25.6,null],[18.2,33.7,31.4,null]],[[16.9,21.0,33.3,null],[10.8,26.9,null,null],[18.2,17.9,null,null],[8.8,24.7,null,null],[13.1,22.7,30.0,null],[0.0,15.7,18.8,null],[22.6,21.6,7.7,null]],[[33.3,25.5,null,null],[2.8,20.0,null,null],[10.0,20.8,null,null],[15.1,14.8,null,null],[13.3,20.0,null,null],[27.5,2.0,null,null],[1.9,18.8,null,null]],[[4.0,35.3,null,null],[8.7,38.2,null,null],[25.0,23.3,null,null],[4.2,41.9,null,null],[26.7,51.7,null,null],[9.7,28.9,null,null],[20.7,23.5,null,null]],[[16.7,41.7,null,null],[3.2,23.7,null,null],[14.3,35.5,null,null],[7.1,51.4,null,null],[25.0,18.2,null,null],[17.9,37.5,null,null],[16.1,34.3,null,null]],[[12.5,31.8,null,null],[26.3,5.0,null,null],[21.7,21.1,null,null],[12.0,26.1,null,null],[23.1,19.2,null,null],[42.1,21.7,null,null],[4.0,16.7,null,null]],[[null,18.5,null,null],[null,10.0,null,null],[null,15.0,null,null],[null,23.1,null,null],[null,9.1,null,null],[null,21.4,null,null],[null,18.5,null,null]],[[23.8,8.6,null,null],[12.5,9.4,null,null],[15.8,11.1,null,null],[19.0,23.5,null,null],[26.3,17.6,null,null],[14.3,19.4,null,null],[13.6,17.6,null,null]],[[18.2,16.3,null,null],[14.3,15.0,null,null],[17.6,21.1,null,null],[15.4,25.0,null,null],[20.6,13.3,null,20.0],[20.0,8.3,null,29.4],[17.1,23.4,null,50.0]],[[15.4,20.7,50.0,33.3],[8.9,18.2,15.4,null],[17.1,22.6,20.0,null],[23.9,36.8,22.2,40.0],[28.0,22.4,26.3,45.5],[25.0,31.1,21.1,46.7],[8.5,53.3,41.2,53.8]]],"monthly":[17.8,18.8,20.9,17.1,15.8,29.8,21.2,20.9,16.2,15.2,14.4,23.9],"arr_monthly":[22.0,20.8,21.9,18.1,16.5,25.5,25.2,19.8,15.9,17.7,19.7,26.2],"monthly_by_year":{"2018":[14.0,12.7,12.3,12.9,19.8,21.0,16.4,8.3,13.5,18.0,22.2,19.6],"2019":[26.1,25.0,21.5,12.3,17.1,23.1,12.9,22.6,15.4,12.2,12.4,12.4],"2020":[10.5,14.8,8.5,6.3,11.1,null,0.0,null,null,null,3.7,17.2],"2021":[10.4,21.7,11.9,14.3,7.7,17.4,19.2,16.2,4.6,21.3,13.8,14.4],"2022":[14.6,23.8,30.2,25.9,12.1,null,null,null,null,null,20.0,41.3],"2023":[18.8,20.5,25.3,16.3,24.4,null,null,null,null,8.6,10.5,18.5],"2024":[25.4,6.8,20.1,22.0,23.8,60.6,48.4,17.2,null,7.3,6.6,33.6],"2025":[12.3,19.7,24.8,8.4,10.1,26.7,30.5,40.4,31.3,23.5,25.9,34.6],"2026":[28.4,24.4,33.5,35.2,null,null,null,null,null,null,null,null]},"monthly_counts":[1540,1248,1471,1029,684,423,446,319,201,438,656,915],"carriers":[{"code":"AA","name":"American Airlines","vol":5367,"dep_delay":12.2,"arr_delay":7.9,"cancel_pct":0.0,"causes":{"carrier":23.2,"weather":3.9,"nas":13.1,"late_aircraft":37.5}},{"code":"UA","name":"United Airlines","vol":3597,"dep_delay":7.2,"arr_delay":0.9,"cancel_pct":0.08,"causes":{"carrier":18.8,"weather":3.6,"nas":24.2,"late_aircraft":29.9}},{"code":"NK","name":"Spirit Airlines","vol":362,"dep_delay":-2.5,"arr_delay":-0.9,"cancel_pct":0.0,"causes":{"carrier":5.8,"weather":0.0,"nas":28.8,"late_aircraft":4.9}}],"annual":{"baseline":[{"year":2018,"arr_delay":2.2,"dep_delay":5.5,"flights":2845},{"year":2019,"arr_delay":4.6,"dep_delay":8.6,"flights":871},{"year":2020,"arr_delay":-6.8,"dep_delay":1.9,"flights":569},{"year":2021,"arr_delay":-0.7,"dep_delay":5.9,"flights":1182},{"year":2022,"arr_delay":11.2,"dep_delay":14.1,"flights":486},{"year":2023,"arr_delay":6.5,"dep_delay":11.6,"flights":665},{"year":2024,"arr_delay":8.8,"dep_delay":14.1,"flights":963},{"year":2025,"arr_delay":10.7,"dep_delay":15.6,"flights":1210},{"year":2026,"arr_delay":16.6,"dep_delay":22.0,"flights":543}],"by_carrier":{"AA":[{"year":2018,"arr_delay":7.2,"dep_delay":8.2,"flights":1578},{"year":2019,"arr_delay":8.3,"dep_delay":10.2,"flights":599},{"year":2020,"arr_delay":-4.3,"dep_delay":3.1,"flights":346},{"year":2021,"arr_delay":-4.6,"dep_delay":5.9,"flights":615},{"year":2022,"arr_delay":12.5,"dep_delay":15.2,"flights":297},{"year":2023,"arr_delay":8.4,"dep_delay":14.7,"flights":392},{"year":2024,"arr_delay":13.1,"dep_delay":17.3,"flights":528},{"year":2025,"arr_delay":14.5,"dep_delay":19.7,"flights":724},{"year":2026,"arr_delay":21.7,"dep_delay":29.1,"flights":272}],"UA":[{"year":2018,"arr_delay":-5.2,"dep_delay":3.8,"flights":905},{"year":2019,"arr_delay":-3.7,"dep_delay":5.1,"flights":272},{"year":2020,"arr_delay":-10.6,"dep_delay":0.1,"flights":223},{"year":2021,"arr_delay":3.4,"dep_delay":5.9,"flights":567},{"year":2022,"arr_delay":9.2,"dep_delay":12.2,"flights":189},{"year":2023,"arr_delay":3.9,"dep_delay":7.3,"flights":273},{"year":2024,"arr_delay":3.4,"dep_delay":10.1,"flights":429},{"year":2025,"arr_delay":4.7,"dep_delay":9.4,"flights":445},{"year":2026,"arr_delay":11.3,"dep_delay":14.9,"flights":271}],"NK":[{"year":2018,"arr_delay":-0.9,"dep_delay":-2.5,"flights":362}]}}}