{"route":{"from":"SBP","to":"SEA","total_flights":3944,"year_min":2018,"year_max":2026},"accuracy":{"dep":{"perfect":82.6,"standard":5.8,"disruptive":11.6},"arr":{"perfect":78.5,"standard":9.3,"disruptive":12.2},"mean_dep_delay":2.3,"mean_arr_delay":-2.3},"accuracy_by_year":{"2018":{"dep":{"perfect":90.8,"standard":2.1,"disruptive":7.1},"arr":{"perfect":90.3,"standard":3.4,"disruptive":6.3}},"2019":{"dep":{"perfect":78.3,"standard":8.2,"disruptive":13.5},"arr":{"perfect":70.9,"standard":14.0,"disruptive":15.1}},"2020":{"dep":{"perfect":87.1,"standard":5.5,"disruptive":7.4},"arr":{"perfect":84.9,"standard":7.7,"disruptive":7.4}},"2021":{"dep":{"perfect":85.6,"standard":5.4,"disruptive":9.0},"arr":{"perfect":82.7,"standard":8.7,"disruptive":8.7}},"2022":{"dep":{"perfect":77.8,"standard":8.0,"disruptive":14.2},"arr":{"perfect":74.0,"standard":11.6,"disruptive":14.4}},"2023":{"dep":{"perfect":78.0,"standard":6.7,"disruptive":15.3},"arr":{"perfect":73.9,"standard":10.2,"disruptive":15.9}},"2024":{"dep":{"perfect":81.3,"standard":6.0,"disruptive":12.7},"arr":{"perfect":72.1,"standard":13.7,"disruptive":14.2}},"2025":{"dep":{"perfect":71.1,"standard":8.1,"disruptive":20.7},"arr":{"perfect":64.7,"standard":10.6,"disruptive":24.6}},"2026":{"dep":{"perfect":82.7,"standard":7.9,"disruptive":9.4},"arr":{"perfect":81.1,"standard":8.7,"disruptive":10.2}}},"insight":"Departure and arrival accuracy track closely on this route \u2014 what leaves late tends to arrive late.","heatmap":[[13.3,9.9,12.4,16.0],[9.7,9.6,5.6,17.6],[8.3,10.3,10.7,20.8],[8.0,12.3,14.3,22.4],[6.2,13.1,13.8,20.4],[6.9,8.3,13.3,21.6],[5.9,10.4,16.7,18.5]],"arr_heatmap":[[16.7,10.4,12.4,22.0],[12.9,10.2,6.5,23.5],[12.5,9.0,11.7,29.2],[8.0,11.7,14.3,22.4],[6.2,13.6,14.7,26.5],[13.8,6.7,14.2,23.5],[0.0,11.2,16.7,27.8]],"monthly_heatmap":[[[null,8.9,7.1,null],[null,4.3,7.7,null],[null,8.9,15.4,null],[null,15.0,21.4,null],[null,4.9,14.3,null],[null,9.8,45.5,null],[null,5.0,23.1,null]],[[null,6.2,null,null],[null,3.1,null,null],[null,6.5,null,null],[null,15.6,null,null],[null,15.6,null,null],[null,6.2,null,null],[null,10.0,null,null]],[[null,8.3,null,null],[null,18.9,null,null],[null,16.2,null,null],[null,7.5,null,null],[null,12.5,null,null],[null,5.1,null,null],[null,10.8,null,20.0]],[[null,4.8,null,null],[null,0.0,null,null],[null,2.6,null,null],[null,15.0,null,null],[null,26.3,null,null],[null,5.6,null,null],[null,2.4,null,null]],[[null,2.9,null,null],[null,13.5,null,null],[null,5.3,null,null],[null,11.1,null,null],[null,11.8,null,null],[null,0.0,null,null],[null,5.7,null,null]],[[null,18.2,null,null],[null,0.0,null,null],[null,2.9,null,null],[null,14.3,null,null],[null,8.1,null,null],[null,9.4,0.0,null],[null,5.9,null,null]],[[null,7.3,null,null],[null,5.6,10.0,null],[null,20.0,25.0,null],[null,0.0,null,null],[null,12.8,20.0,null],[null,16.7,15.8,null],[null,9.8,null,null]],[[null,13.8,10.0,null],[null,12.0,0.0,null],[null,12.9,null,null],[null,25.0,10.0,null],[null,16.1,null,null],[null,4.2,7.7,null],[null,21.4,0.0,null]],[[null,16.7,null,null],[null,14.3,null,null],[null,13.3,null,null],[null,6.7,null,null],[null,13.3,null,null],[null,13.8,null,null],[null,16.1,null,null]],[[null,13.6,null,null],[null,13.6,0.0,null],[null,18.2,0.0,null],[null,13.6,20.0,null],[null,9.1,null,null],[null,12.5,null,null],[null,14.3,null,null]],[[null,13.0,0.0,null],[null,26.1,null,null],[null,9.1,0.0,null],[null,12.5,null,null],[null,20.8,0.0,null],[null,4.8,0.0,null],[null,19.0,20.0,null]],[[null,11.8,33.3,null],[null,18.8,6.7,null],[null,13.3,13.3,null],[null,14.3,26.7,null],[null,0.0,18.8,null],[null,16.7,13.3,null],[null,17.6,33.3,null]]],"arr_monthly_heatmap":[[[null,8.9,7.1,null],[null,8.7,7.7,null],[null,8.9,23.1,null],[null,17.5,21.4,null],[null,9.8,7.1,null],[null,4.9,36.4,null],[null,2.5,7.7,null]],[[null,6.2,null,null],[null,6.2,null,null],[null,6.5,null,null],[null,18.8,null,null],[null,15.6,null,null],[null,6.2,null,null],[null,13.3,null,null]],[[null,2.8,null,null],[null,5.4,null,null],[null,10.8,null,null],[null,2.5,null,null],[null,15.0,null,null],[null,2.6,null,null],[null,10.8,null,10.0]],[[null,7.1,null,null],[null,2.6,null,null],[null,0.0,null,null],[null,15.0,null,null],[null,31.6,null,null],[null,5.6,null,null],[null,4.9,null,null]],[[null,8.6,null,null],[null,18.9,null,null],[null,7.9,null,null],[null,8.3,null,null],[null,8.8,null,null],[null,0.0,null,null],[null,8.6,null,null]],[[null,24.2,null,null],[null,2.9,null,null],[null,2.9,null,null],[null,17.1,null,null],[null,5.4,null,null],[null,9.4,7.7,null],[null,17.6,null,null]],[[null,7.3,null,null],[null,5.6,10.0,null],[null,14.3,16.7,null],[null,0.0,null,null],[null,2.6,20.0,null],[null,13.3,10.5,null],[null,2.4,null,null]],[[null,13.8,20.0,null],[null,8.0,0.0,null],[null,19.4,null,null],[null,25.0,10.0,null],[null,16.1,null,null],[null,8.3,15.4,null],[null,25.0,0.0,null]],[[null,13.3,null,null],[null,10.7,null,null],[null,13.3,null,null],[null,6.7,null,null],[null,23.3,null,null],[null,10.3,null,null],[null,16.1,null,null]],[[null,18.2,null,null],[null,22.7,0.0,null],[null,18.2,0.0,null],[null,9.1,20.0,null],[null,9.1,null,null],[null,12.5,null,null],[null,14.3,null,null]],[[null,8.7,0.0,null],[null,21.7,null,null],[null,4.5,10.0,null],[null,12.5,null,null],[null,16.7,0.0,null],[null,4.8,9.1,null],[null,14.3,30.0,null]],[[null,11.8,26.7,null],[null,25.0,13.3,null],[null,0.0,20.0,null],[null,7.1,26.7,null],[null,7.1,18.8,null],[null,5.6,20.0,null],[null,17.6,26.7,null]]],"monthly":[13.8,13.0,12.6,7.5,9.8,12.6,13.1,15.7,12.9,14.7,12.2,16.5],"arr_monthly":[10.1,10.6,9.2,10.6,11.8,13.4,9.3,16.7,12.6,17.3,11.3,17.7],"monthly_by_year":{"2018":[3.2,0.0,9.7,10.3,3.2,6.7,6.5,22.6,10.0,12.9,10.0,16.1],"2019":[22.6,25.0,9.7,3.3,16.1,6.7,9.7,9.7,6.7,16.1,23.3,16.1],"2020":[9.7,17.2,16.1,0.0,6.5,3.3,6.5,3.2,10.0,3.2,3.3,9.7],"2021":[6.5,12.0,8.9,3.3,9.7,3.3,17.5,3.6,10.8,12.9,10.3,17.2],"2022":[20.7,7.1,9.7,13.3,3.2,15.6,11.3,10.4,23.4,20.6,16.2,17.2],"2023":[13.3,14.3,16.1,3.3,12.9,14.8,12.9,25.8,20.0,16.1,14.6,19.4],"2024":[28.6,16.0,10.4,15.1,7.4,10.0,11.3,14.8,11.1,19.4,3.4,16.1],"2025":[6.7,18.5,16.1,16.7,19.4,40.0,29.0,35.5,11.1,16.7,16.7,20.0],"2026":[12.9,7.1,16.7,2.6,null,null,null,null,null,null,null,null]},"monthly_counts":[396,302,371,388,364,372,398,319,285,250,256,243],"carriers":[{"code":"AS","name":"Alaska Airlines","vol":3944,"dep_delay":2.4,"arr_delay":-2.3,"cancel_pct":0.0,"causes":{"carrier":17.0,"weather":1.9,"nas":9.7,"late_aircraft":37.8}}],"annual":{"baseline":[{"year":2018,"arr_delay":-13.6,"dep_delay":-2.1,"flights":848},{"year":2019,"arr_delay":-0.9,"dep_delay":3.1,"flights":364},{"year":2020,"arr_delay":-5.5,"dep_delay":-1.8,"flights":365},{"year":2021,"arr_delay":-4.1,"dep_delay":0.2,"flights":520},{"year":2022,"arr_delay":1.7,"dep_delay":5.2,"flights":450},{"year":2023,"arr_delay":5.6,"dep_delay":8.1,"flights":372},{"year":2024,"arr_delay":3.2,"dep_delay":4.4,"flights":534},{"year":2025,"arr_delay":8.6,"dep_delay":7.7,"flights":357},{"year":2026,"arr_delay":-5.4,"dep_delay":-0.2,"flights":127}],"by_carrier":{"AS":[{"year":2018,"arr_delay":-13.6,"dep_delay":-2.1,"flights":848},{"year":2019,"arr_delay":-0.9,"dep_delay":3.1,"flights":364},{"year":2020,"arr_delay":-5.5,"dep_delay":-1.8,"flights":365},{"year":2021,"arr_delay":-4.1,"dep_delay":0.2,"flights":520},{"year":2022,"arr_delay":1.7,"dep_delay":5.2,"flights":450},{"year":2023,"arr_delay":5.6,"dep_delay":8.1,"flights":372},{"year":2024,"arr_delay":3.2,"dep_delay":4.4,"flights":534},{"year":2025,"arr_delay":8.6,"dep_delay":7.7,"flights":357},{"year":2026,"arr_delay":-5.4,"dep_delay":-0.2,"flights":127}]}}}